MANIFEST.in
setup.cfg
setup.py
jzfp_conflict_demo/__init__.py
jzfp_conflict_demo/main.py
jzfp_conflict_mkt_title_demo.egg-info/PKG-INFO
jzfp_conflict_mkt_title_demo.egg-info/SOURCES.txt
jzfp_conflict_mkt_title_demo.egg-info/dependency_links.txt
jzfp_conflict_mkt_title_demo.egg-info/top_level.txt