Metadata-Version: 1.0
Name: jzfp-conflict-mkt-title-demo
Version: 1.0.0
Summary: A demo for python packaging.
Home-page: https://github.com/***/***
Author: liuyaqi
Author-email: yaqi_617@163.com
License: JD617
Keywords: jzfp_conflict
Platform: UNKNOWN
